LICENSE
README.md
setup.cfg
setup.py
keeper_secrets_manager_hsm/__init__.py
keeper_secrets_manager_hsm/storage_aws_kms.py
keeper_secrets_manager_hsm/storage_hsm_nfast.py
keeper_secrets_manager_storage/__init__.py
keeper_secrets_manager_storage/config_provider.py
keeper_secrets_manager_storage/storage_aws_secret.py
keeper_secrets_manager_storage/storage_azure_keyvault.py
keeper_secrets_manager_storage.egg-info/PKG-INFO
keeper_secrets_manager_storage.egg-info/SOURCES.txt
keeper_secrets_manager_storage.egg-info/dependency_links.txt
keeper_secrets_manager_storage.egg-info/not-zip-safe
keeper_secrets_manager_storage.egg-info/requires.txt
keeper_secrets_manager_storage.egg-info/top_level.txt