Metadata-Version: 2.1
Name: keeper-secrets-manager-storage
Version: 1.0.2
Summary: Keeper Secrets Manager SDK helper for managing configurations key-value storage.
Home-page: https://github.com/Keeper-Security/secrets-manager
Author: Keeper Security
Author-email: sm@keepersecurity.com
License: MIT
Project-URL: Bug Tracker, https://github.com/Keeper-Security/secrets-manager/issues
Project-URL: Documentation, https://docs.keeper.io/secrets-manager/secrets-manager/overview
Project-URL: Source Code, https://github.com/Keeper-Security/secrets-manager
Keywords: Keeper Password Secrets Manager Storage Key-Value HSM
Classifier: Development Status :: 4 - Beta
Classifier: Intended Audience :: Developers
Classifier: License :: OSI Approved :: MIT License
Classifier: Operating System :: OS Independent
Classifier: Programming Language :: Python
Classifier: Programming Language :: Python :: 3
Classifier: Programming Language :: Python :: 3.6
Classifier: Programming Language :: Python :: 3.7
Classifier: Programming Language :: Python :: 3.8
Classifier: Programming Language :: Python :: 3.9
Classifier: Topic :: Security
Requires-Python: >=3.6
License-File: LICENSE
